problem_report_extraction/EventStreamDataExtractor.py
problem_report_extraction/HWErrorsFromSyslog.py
problem_report_extraction/__init__.py
problem_report_extraction/extract.py
problem_report_extraction/test.py
shared_data_handling/__init__.py
shared_data_handling/find_files.py
shared_data_handling/handle_file.py
shared_data_handling/handle_folder.py
shared_data_handling/process_data.py
tests/DataExtraction_test.py
tests/__init__.py
shared_data_handling-0.1.3.dist-info/LICENCE
shared_data_handling-0.1.3.dist-info/METADATA
shared_data_handling-0.1.3.dist-info/WHEEL
shared_data_handling-0.1.3.dist-info/top_level.txt
shared_data_handling-0.1.3.dist-info/RECORD
