Metadata-Version: 2.1
Name: shared-data-handling
Version: 0.1.3
Summary: a lib to facilitate file handling and data extraction from log files
Home-page: https://code.roche.com/pcr-hw-development-tools/shared-tools/SharedDataHandling
Author: Fabian Roth
Author-email: fabian.roth.fr1@roche.com
License: UNKNOWN
Project-URL: homepage, https://code.roche.com/pcr-hw-development-tools/shared-tools/SharedDataHandling
Project-URL: changelog, https://code.roche.com/pcr-hw-development-tools/shared-tools/SharedDataHandling
Project-URL: Bug Tracker, https://code.roche.com/pcr-hw-development-tools/shared-tools/SharedDataHandling/-/issues
Platform: UNKNOWN
Classifier: License :: OSI Approved :: MIT License
Classifier: Programming Language :: Python :: 3
Classifier: Programming Language :: Python :: 3 :: Only
Classifier: Programming Language :: Python :: 3.9
Classifier: Programming Language :: Python :: 3.10
Classifier: Programming Language :: Python :: Implementation :: CPython
Classifier: Programming Language :: Python :: Implementation :: PyPy
Requires-Python: >=3.6
License-File: LICENCE
